README.md
setup.py
webmontage/__init__.py
webmontage/command.py
webmontage.egg-info/PKG-INFO
webmontage.egg-info/SOURCES.txt
webmontage.egg-info/dependency_links.txt
webmontage.egg-info/entry_points.txt
webmontage.egg-info/requires.txt
webmontage.egg-info/top_level.txt