Metadata-Version: 2.1
Name: webmontage
Version: 1.0.0
Summary: Web page montage generator
Home-page: https://github.com/dylanfw/webmontage
Author: Dylan Williams
Author-email: dylan@dylanfw.com
License: UNKNOWN
Platform: UNKNOWN
Classifier: Programming Language :: Python :: 3
Classifier: License :: OSI Approved :: MIT License
Classifier: Operating System :: OS Independent
